bopi/__init__.py
bopi-0.0.1.dist-info/LICENSE
bopi-0.0.1.dist-info/METADATA
bopi-0.0.1.dist-info/WHEEL
bopi-0.0.1.dist-info/top_level.txt
bopi-0.0.1.dist-info/RECORD
